pyrussh-0.1.0.dist-info/METADATA
pyrussh-0.1.0.dist-info/WHEEL
pyrussh-0.1.0.dist-info/license_files/LICENSE
pyrussh-0.1.0.dist-info/license_files/LICENSE-APACHE
pyrussh/pool.py
pyrussh/__init__.py
pyrussh/_pyssh.cpython-310-x86_64-linux-gnu.so
pyrussh-0.1.0.dist-info/RECORD
